{"dragon": {"capsule": null, "mass_returned_kg": null, "mass_returned_lbs": null, "flight_time_sec": null, "manifest": null, "water_landing": null, "land_landing": null}, "name": "GovSat-1", "type": "Satellite", "reused": false, "launch": "5eb87d11ffd86e000604b35f", "customers": ["GovSat"], "norad_ids": [43178], "nationalities": ["Luxembourg"], "manufacturers": ["Orbital ATK"], "mass_kg": 4230, "mass_lbs": 9325.6, "orbit": "GTO", "reference_system": "geocentric", "regime": "geostationary", "longitude": 21.5, "semi_major_axis_km": null, "eccentricity": null, "periapsis_km": null, "apoapsis_km": null, "inclination_deg": null, "period_min": null, "lifespan_years": 15, "epoch": null, "mean_motion": null, "raan": null, "arg_of_pericenter": null, "mean_anomaly": null, "id": "5eb0e4c6b6c3bb0006eeb21b"}